zmp_md_translator/__init__.py
zmp_md_translator/logging_setup.py
zmp_md_translator/main.py
zmp_md_translator/markdown_translator.py
zmp_md_translator/scripts.py
zmp_md_translator/settings.py
zmp_md_translator/types.py
zmp_md_translator/utils/__init__.py
zmp_md_translator/utils/git_utils.py
zmp_md_translator-0.2.8.dist-info/LICENSE
zmp_md_translator-0.2.8.dist-info/METADATA
zmp_md_translator-0.2.8.dist-info/WHEEL
zmp_md_translator-0.2.8.dist-info/entry_points.txt
zmp_md_translator-0.2.8.dist-info/RECORD
