Metadata-Version: 2.3
Name: zmp-md-translator
Version: 0.2.8
Summary: A high-performance markdown translator that supports multiple languages and preserves markdown formatting.
Author: stiron
Author-email: lesch1@gmail.com
Requires-Python: >=3.11,<4.0
Classifier: Programming Language :: Python :: 3
Classifier: Programming Language :: Python :: 3.11
Classifier: Programming Language :: Python :: 3.12
Classifier: Programming Language :: Python :: 3.13
Requires-Dist: aiofiles (>=24.1.0,<25.0.0)
Requires-Dist: colorlog (>=6.9.0,<7.0.0)
Requires-Dist: fastapi (>=0.110.0,<0.111.0)
Requires-Dist: httpx (>=0.28.1,<0.29.0)
Requires-Dist: openai (>=1.12.0,<2.0.0)
Requires-Dist: pydantic (>=2.0.0,<3.0.0)
Requires-Dist: pydantic-settings (>=2.2.1,<3.0.0)
Requires-Dist: python-dotenv (>=1.0.1,<2.0.0)
Requires-Dist: python-multipart (>=0.0.9,<0.0.10)
Requires-Dist: uvicorn (>=0.27.1,<0.28.0)
